jk_datamatrix/DataMatrix.py
jk_datamatrix/DataMatrixCSVWriter.py
jk_datamatrix/DataMatrixJSONLoader.py
jk_datamatrix/DataMatrixJSONWriter.py
jk_datamatrix/DataMatrixRow.py
jk_datamatrix/ICSVMixin.py
jk_datamatrix/IJSONMixin.py
jk_datamatrix/_IDataMatrix.py
jk_datamatrix/__init__.py
jk_datamatrix-0.2025.5.25.dist-info/WHEEL
jk_datamatrix-0.2025.5.25.dist-info/METADATA
jk_datamatrix-0.2025.5.25.dist-info/RECORD
