Metadata-Version: 2.1
Name: jk_datamatrix
Version: 0.2025.5.25
Summary: This python module provides a class that represents a data matrix. This is basically a table you can work with: Modify, sort, filter and print. Everthing is kept in memory, is not indexed, and therefore intended for a limited amount of data only.
Keywords: matrix,table,data,datatable
Author-email: Jürgen Knauth <pubsrc@binary-overflow.de>
Maintainer-email: Jürgen Knauth <pubsrc@binary-overflow.de>
Requires-Python: >=3.8
Classifier: Development Status :: 3 - Alpha
Classifier: License :: OSI Approved :: Apache Software License
Classifier: Programming Language :: Python :: 3
Requires-Dist: jk_console
Requires-Dist: jk_typing
Requires-Dist: jk_json
